ppig/__init__.py
ppig/main.py
ppig/utils.py
ppig-0.2.2.dist-info/METADATA
ppig-0.2.2.dist-info/WHEEL
ppig-0.2.2.dist-info/entry_points.txt
ppig-0.2.2.dist-info/RECORD
