Metadata-Version: 2.1
Name: ppig
Version: 0.2.2
Summary: An AI terminal assistant
Author: Miguel Martín
Author-email: miguel.martinr11@gmail.com
Requires-Python: >=3.8,<4.0
Classifier: Programming Language :: Python :: 3
Classifier: Programming Language :: Python :: 3.8
Classifier: Programming Language :: Python :: 3.9
Classifier: Programming Language :: Python :: 3.10
Classifier: Programming Language :: Python :: 3.11
Requires-Dist: openai (>=0.27.2,<0.28.0)
Requires-Dist: pyperclip (>=1.8.2,<2.0.0)
Requires-Dist: pyyaml (>=6.0,<7.0)
Requires-Dist: requests (>=2.28.2,<3.0.0)
